jupyter_drives/__init__.py
jupyter_drives/_version.py
jupyter_drives/base.py
jupyter_drives/handlers.py
jupyter_drives/log.py
jupyter_drives/manager.py
jupyter_drives/tests/__init__.py
jupyter_drives/tests/test_extensions.py
jupyter_drives/tests/test_handlers.py
jupyter_drives-0.2.0.data/data/etc/jupyter/jupyter_server_config.d/jupyter_drives.json
jupyter_drives-0.2.0.data/data/share/jupyter/labextensions/jupyter-drives/package.json
jupyter_drives-0.2.0.data/data/share/jupyter/labextensions/jupyter-drives/schemas/jupyter-drives/drives-file-browser.json
jupyter_drives-0.2.0.data/data/share/jupyter/labextensions/jupyter-drives/schemas/jupyter-drives/package.json.orig
jupyter_drives-0.2.0.data/data/share/jupyter/labextensions/jupyter-drives/static/174.9960894c0fcb86812bb6.js
jupyter_drives-0.2.0.data/data/share/jupyter/labextensions/jupyter-drives/static/728.14193e9a2c37eb9c46d4.js
jupyter_drives-0.2.0.data/data/share/jupyter/labextensions/jupyter-drives/static/remoteEntry.91d24c33bbef88f06df9.js
jupyter_drives-0.2.0.data/data/share/jupyter/labextensions/jupyter-drives/static/style.js
jupyter_drives-0.2.0.data/data/share/jupyter/labextensions/jupyter-drives/static/third-party-licenses.json
jupyter_drives-0.2.0.data/data/share/jupyter/labextensions/jupyter-drives/install.json
jupyter_drives-0.2.0.dist-info/METADATA
jupyter_drives-0.2.0.dist-info/WHEEL
jupyter_drives-0.2.0.dist-info/entry_points.txt
jupyter_drives-0.2.0.dist-info/licenses/LICENSE
jupyter_drives-0.2.0.dist-info/RECORD
