Metadata-Version: 2.4
Name: jupyter_drives
Version: 0.2.0
Dynamic: Keywords
Summary: A Jupyter extension to support drives in the backend.
Project-URL: Homepage, https://github.com/QuantStack/jupyter-drives
Project-URL: Bug Tracker, https://github.com/QuantStack/jupyter-drives/issues
Project-URL: Repository, https://github.com/QuantStack/jupyter-drives.git
Author: Jupyter Contribution Team
License: BSD 3-Clause License
License-File: LICENSE
Classifier: Framework :: Jupyter
Classifier: Framework :: Jupyter :: JupyterLab
Classifier: Framework :: Jupyter :: JupyterLab :: 4
Classifier: Framework :: Jupyter :: JupyterLab :: Extensions
Classifier: Framework :: Jupyter :: JupyterLab :: Extensions :: Prebuilt
Classifier: License :: OSI Approved :: BSD License
Classifier: Programming Language :: Python
Classifier: Programming Language :: Python :: 3
Classifier: Programming Language :: Python :: 3.8
Classifier: Programming Language :: Python :: 3.9
Classifier: Programming Language :: Python :: 3.10
Classifier: Programming Language :: Python :: 3.11
Requires-Python: >=3.8
Requires-Dist: aiobotocore<2.16.0,>=2.15.2
Requires-Dist: apache-libcloud<4,>=3.8.0
Requires-Dist: arro3-core<0.3,>=0.2.1
Requires-Dist: boto3<1.36.0,>=1.35.36
Requires-Dist: entrypoints<0.5,>=0.4
Requires-Dist: fsspec<2024.11.0,>=2024.10.0
Requires-Dist: httpx<0.26,>=0.25.1
Requires-Dist: jupyter-server<3,>=2.14.2
Requires-Dist: obstore<0.4,>=0.3.0b
Requires-Dist: pyarrow<19.0.0,>=18.0.0
Requires-Dist: s3fs<2024.11.0,>=2024.10.0
Provides-Extra: test
Requires-Dist: coverage; extra == 'test'
Requires-Dist: mock>=4.0.0; extra == 'test'
Requires-Dist: moto[server]>=4.2.8; extra == 'test'
Requires-Dist: pytest; extra == 'test'
Requires-Dist: pytest-asyncio; extra == 'test'
Requires-Dist: pytest-cov; extra == 'test'
Requires-Dist: pytest-jupyter[server]>=0.6.0; extra == 'test'
